fupi/__init__.py
fupi/fupi.py
fupi-1.40.1.dist-info/licenses/LICENSE
fupi-1.40.1.dist-info/METADATA
fupi-1.40.1.dist-info/WHEEL
fupi-1.40.1.dist-info/top_level.txt
fupi-1.40.1.dist-info/RECORD
