Metadata-Version: 2.4
Name: fupi
Version: 1.40.1
Summary: A brute-force shortcut to fix python import hell. Acronym, standing for, um, Fix Up Python Imports. Sure, let's go with that.
Author-email: Stephen Hilton <stephen@familyhilton.com>
License-Expression: MIT
Keywords: python,imports,import,hell
Requires-Python: >=3.11
License-File: LICENSE
Dynamic: license-file
